{
  "detail_url": "https://swatchon.com/wholesale-fabric/Polyester-Spandex+-+Elastane-Woven-Dobby-Crinkled+-+Puckered+-+Rippled-43095",
  "image_src": "https://d1fnkfov8k8p66.cloudfront.net/images/small/PD-00573613_e0a6d941-03d9-45a5-b1e7-dff100662941_IMG_2857+2.jpg",
  "specifications": {
    "Fabric Type": "Woven > Dobby",
    "Fiber Content": "Polyester 98% / Spandex 2%",
    "Pattern": "Stripes",
    "Dimensions": "128 gsm",
    "Weight": "57 in",
    "Width": "0.38 mm",
    "Characteristics": "Appearance > Puckered",
    "Dye Method": "Yarn Dye Yarn dye is the process of coloring yarn before it is used to make fabric. It results in even color and enhanced color fastness in the finished fabric.",
    "Care Instructions": "Hand wash only Wash separately Turn inside out before washing, Do not wring, Do not rub Do not bleach Flat dry Do not iron",
    "Country": "Korea"
  },
  "tags": [
    "#Bubble"
  ]
}