{
  "detail_url": "https://swatchon.com/wholesale-fabric/Cotton-Woven-Dobby-Printed-47282",
  "image_src": "https://d1fnkfov8k8p66.cloudfront.net/images/small/PD-00616919_499dde24-2dda-4211-87c2-5013e33bef38_IMG_4744+2.jpg",
  "specifications": {
    "Fabric Type": "Woven > Dobby",
    "Fiber Content": "Cotton 100%",
    "Pattern": "Floral",
    "Dimensions": "84 gsm",
    "Weight": "50 in",
    "Width": "0.27 mm",
    "Dye Method": "Printed",
    "Care Instructions": "Hand wash only Wash separately Turn inside out before washing, Do not wring, Do not rub Do not bleach Flat dry Do not iron",
    "Country": "Korea"
  }
}