{
  "detail_url": "https://swatchon.com/wholesale-fabric/Cotton-Polyester-Knit-Pique-30777",
  "image_src": "https://d1fnkfov8k8p66.cloudfront.net/images/small/450a81aa-867e-496f-82d6-aec0e63332af.jpg",
  "specifications": {
    "Fabric Type": "Knit > Pique",
    "Fiber Content": "Cotton 71% / Polyester 29%",
    "Pattern": "Solid",
    "Dimensions": "200 gsm",
    "Weight": "54 in",
    "Width": "0.62 mm",
    "Dye Method": "Piece Dye",
    "Care Advice": "Knit When you receive a knit product, it may be stiff and wrinkled. This is because the fabric has been folded and compressed for shipping. To soften and straighten the fabric, you should condition it for 2-3 days at room temperature before using it.",
    "Care Instructions": "Machine wash cold / Gentle Wash with similar colors Non-chlorine bleach when needed, for whites only Tumble dry normal low heat Do not iron Sustainability Eco-forward > Dead Stock This fabric is deadstock (leftover from previous productions) and will not be restocked after selling out. Recommended Use T-shirts, Activewear",
    "Country": "Korea"
  },
  "tags": [
    "#Kids"
  ]
}