{
  "detail_url": "https://swatchon.com/wholesale-fabric/Metallic-Nylon-Knit-Mesh-Tulle-Metallic-21973",
  "image_src": "https://d1fnkfov8k8p66.cloudfront.net/images/small/PD-00244353-3c403947-253a-49dc-a1dd-8c20f65107ce.jpg",
  "specifications": {
    "Fabric Type": "Knit > Mesh",
    "Fiber Content": "Nylon 88% / Metallic 12%",
    "Pattern": "Solid",
    "Dimensions": "36 gsm",
    "Weight": "58 in",
    "Width": "0.29 mm",
    "Characteristics": "Yarn Effect > Metallic Yarn",
    "Dye Method": "Piece Dye",
    "Care Advice": "Knit When you receive a knit product, it may be stiff and wrinkled. This is because the fabric has been folded and compressed for shipping. To soften and straighten the fabric, you should condition it for 2-3 days at room temperature before using it. Yarn Effect > Metallic Yarn Please be careful not to pull threads when using this fabric, due to its nature of this fabric.",
    "Care Instructions": "Hand wash only Wash separately Turn inside out before washing, Do not wring, Do not rub Do not bleach Tumble dry normal low heat Do not iron Recommended Use Partywear",
    "Country": "Korea"
  },
  "tags": [
    "#Openwork"
  ]
}