{
  "detail_url": "https://swatchon.com/wholesale-fabric/Polyester-Nylon-Knit-Mesh-Printed-38212",
  "image_src": "https://d1fnkfov8k8p66.cloudfront.net/images/small/PD-00500690_99d3c4b5-efb2-4ab9-8651-8302728761f3_IMG_7289+2.jpg",
  "specifications": {
    "Fabric Type": "Knit > Mesh",
    "Fiber Content": "Polyester 75% / Nylon 25%",
    "Pattern": "Animal Pattern",
    "Dimensions": "165 gsm",
    "Weight": "58 in",
    "Width": "0.49 mm",
    "Dye Method": "Printed",
    "Care Advice": "Knit When you receive a knit product, it may be stiff and wrinkled. This is because the fabric has been folded and compressed for shipping. To soften and straighten the fabric, you should condition it for 2-3 days at room temperature before using it.",
    "Care Instructions": "Hand wash only Wash separately Turn inside out before washing, Do not wring, Do not rub Do not bleach Tumble dry normal low heat Do not iron",
    "Country": "Korea"
  },
  "tags": [
    "#Leopard",
    "#Openwork"
  ]
}