{
  "detail_url": "https://swatchon.com/wholesale-fabric/Cotton-Knit-Mesh-Piece+dye-43928",
  "image_src": "https://d1fnkfov8k8p66.cloudfront.net/images/small/PD-00586911_1f45af91-c0c1-414f-b77a-20eccb939d21_IMG_8329+2.jpg",
  "specifications": {
    "Fabric Type": "Knit > Mesh",
    "Fiber Content": "Cotton 100%",
    "Pattern": "Solid",
    "Dimensions": "140 gsm",
    "Weight": "56 in",
    "Width": "0.58 mm",
    "Finish": "Chemical > Enzyme Enzymes treatment offers a remarkably soft hand-feel by gently breaking down the fibers’ surface, resulting in a smoother and cleaner texture. This treatment also reduces pilling and fuzz, enhancing the fabric’s durability and maintaining a clean appearance",
    "Dye Method": "Piece Dye",
    "Care Advice": "Knit When you receive a knit product, it may be stiff and wrinkled. This is because the fabric has been folded and compressed for shipping. To soften and straighten the fabric, you should condition it for 2-3 days at room temperature before using it. Chemical > Enzyme Piece printing on enzyme/bio-washed fabric can cause staining. Therefore, please refrain from piece printing on this fabric.",
    "Care Instructions": "Hand wash only Wash separately Do not wring, Do not rub Do not bleach Tumble dry normal low heat Do not iron",
    "Country": "Korea"
  },
  "tags": [
    "#Openwork"
  ]
}