{
  "detail_url": "https://swatchon.com/wholesale-fabric/Linen-Cotton-Plain-Gauze-Piece+Dye-50930",
  "image_src": "https://d1fnkfov8k8p66.cloudfront.net/images/small/PD-00689803_742cdfcc-a20e-4926-8c07-cb7b73967e2a_IMG_1089.jpg",
  "specifications": {
    "Fabric Type": "Woven > Plain > Gauze",
    "Fiber Content": "Linen 55% / Cotton 45%",
    "Pattern": "Solid",
    "Dimensions": "107 gsm",
    "Weight": "53 in",
    "Width": "0.24 mm",
    "Dye Method": "Piece Dye",
    "Care Advice": "Natural > Plant > Linen Linen fabric is made from natural materials, so it may have small bumps (slubs) in it. It is also important to keep linen fabric dry, because it can shrink or become misshapen if it gets wet. Store linen fabric in a cool, dry place where it can get plenty of air.",
    "Care Instructions": "Dry clean only Recommended Use Blouses",
    "Country": "Korea"
  }
}