{
  "detail_url": "https://swatchon.com/wholesale-fabric/Cotton-Woven-Corduroy-25939",
  "image_src": "https://d1fnkfov8k8p66.cloudfront.net/images/small/PD-00625070_49bef7da-8e0b-4d01-bf86-92273adedadd_IMG_8859.jpg",
  "specifications": {
    "Fabric Type": "Woven > Pile Weave > Corduroy",
    "Fiber Content": "Cotton 100%",
    "Pattern": "Solid",
    "Dimensions": "304 gsm",
    "Weight": "56 in",
    "Width": "1.03 mm",
    "Dye Method": "Piece Dye",
    "Care Instructions": "Machine wash cold / Gentle Wash with similar colors Turn inside out before washing Non-chlorine bleach when needed, for whites only Tumble dry normal low heat Iron on low heat on reverse side if needed Recommended Use Outer",
    "Country": "Korea"
  }
}