{
  "detail_url": "https://swatchon.com/wholesale-fabric/Cotton-Woven-Eyelet-Piece+Dye-51763",
  "image_src": "https://d1fnkfov8k8p66.cloudfront.net/images/small/PD-00715901_9edcc540-ceb5-47d9-90f1-8406576ff631_IMG_6273+3.jpg",
  "specifications": {
    "Fabric Type": "Woven > Eyelet",
    "Fiber Content": "Cotton 100%",
    "Pattern": "Abstract",
    "Dimensions": "144 gsm",
    "Weight": "50 in",
    "Width": "0.22 mm",
    "Finish": "Decoration > Embroidery Embroidery is a decorative finishing that uses different stitches, yarns, and materials to create patterns on the fabric. This process adds visual interest, texture, and a handcrafted feel.",
    "Dye Method": "Piece Dye",
    "Care Instructions": "Hand wash only Wash separately Turn inside out before washing, Do not wring Non-chlorine bleach when needed, for whites only Line dry Do not tumble dry Iron on low heat on reverse side if needed Recommended Use Bridal, Dresses",
    "Country": "Korea"
  }
}