{
  "detail_url": "https://swatchon.com/wholesale-fabric/Wool-Woven-Double+weave-Yarn+dye-34811",
  "image_src": "https://d1fnkfov8k8p66.cloudfront.net/images/small/PD-00460598_f6c87bda-b9ac-4a27-874a-5f4cb84f5181_IMG_5366.jpg",
  "specifications": {
    "Fabric Type": "Woven > Double Weave",
    "Fiber Content": "Wool 100%",
    "Pattern": "Solid",
    "Dimensions": "314 gsm",
    "Weight": "57 in",
    "Width": "0.7 mm",
    "Dye Method": "Yarn Dye Yarn dye is the process of coloring yarn before it is used to make fabric. It results in even color and enhanced color fastness in the finished fabric. Yarn Effect > Worsted Yarn Worsted is a high-quality type of wool yarn, typically made from long-staple pasture wool. It is commonly used in the production of tailored garments, such as suits. In tropical-weight worsteds, tightly spun and straightened wool, combined with a looser weave, allows for better airflow through the fabric.",
    "Care Instructions": "Dry clean only Recommended Use Coats",
    "Country": "Korea"
  }
}