{
  "detail_url": "https://swatchon.com/wholesale-fabric/Polyester-Viscose+rayon-Spandex+-+Elastane-Woven-Double+weave-Piece+dye-35093",
  "image_src": "https://d1fnkfov8k8p66.cloudfront.net/images/small/PD-00464446_9eb8ab7c-77ab-49e8-b2ee-1288324b1f73_IMG_2392.jpg",
  "specifications": {
    "Fabric Type": "Woven > Double Weave",
    "Fiber Content": "Polyester 81% / Viscose Rayon 15% / Spandex 4%",
    "Pattern": "Solid",
    "Dimensions": "183 gsm",
    "Weight": "57 in",
    "Width": "0.7 mm",
    "Dye Method": "Piece Dye",
    "Care Advice": "Regenerated > Viscose Rayon This fabric can shrink or become distorted if it get wet. Store it in a cool, dry, well-ventilated location.",
    "Care Instructions": "Dry clean only",
    "Country": "Korea"
  }
}