{
  "detail_url": "https://swatchon.com/wholesale-fabric/Triacetate-Polyester-Woven-Double+weave-Piece+dye-36431",
  "image_src": "https://d1fnkfov8k8p66.cloudfront.net/images/small/PD-00476950_bb75d39f-446d-43a4-9a63-5978dccf6fb4_IMG_4070.jpg",
  "specifications": {
    "Fabric Type": "Woven > Double Weave",
    "Fiber Content": "Triacetate 63% / Polyester 37%",
    "Pattern": "Solid",
    "Dimensions": "230 gsm",
    "Weight": "58 in",
    "Width": "0.55 mm",
    "Dye Method": "Piece Dye",
    "Care Advice": "Regenerated > Triacetate This fabric is easy to damage, so be careful when handling it and keep it dry. It may shrink or become misshapen if it gets wet. Store it in a cool, dry place where it can get plenty of air.",
    "Care Instructions": "Dry clean only",
    "Country": "Korea"
  }
}